ctyun_openapi_sdk_core/__init__.py
ctyun_openapi_sdk_core/client_config.py
ctyun_openapi_sdk_core/credential.py
ctyun_openapi_sdk_core/ctyun_client.py
ctyun_openapi_sdk_core/ctyun_openapi_response.py
ctyun_openapi_sdk_core/exception.py
ctyun_openapi_sdk_core/request.py
ctyun_openapi_sdk_core/sign_util.py
ctyun_openapi_sdk_core-0.0.1.dist-info/licenses/LICENSE
ctyun_openapi_sdk_core-0.0.1.dist-info/METADATA
ctyun_openapi_sdk_core-0.0.1.dist-info/WHEEL
ctyun_openapi_sdk_core-0.0.1.dist-info/top_level.txt
ctyun_openapi_sdk_core-0.0.1.dist-info/RECORD
