Metadata-Version: 2.4
Name: ctyun_openapi_sdk_core
Version: 0.0.1
Summary: A simple example package
Author-email: ctyunsdk <ctyunsdk@chinatelecom.cn>
License: MIT
Project-URL: Homepage, https://github.com/ctyunsdk/ctyun-python-sdk-core
Project-URL: Repository, https://github.com/ctyunsdk/ctyun-python-sdk-core
Classifier: Programming Language :: Python :: 3
Classifier: License :: OSI Approved :: MIT License
Classifier: Operating System :: OS Independent
Requires-Python: >=3.9
License-File: LICENSE
Requires-Dist: requests>=2.32.5
Requires-Dist: dataclasses_json>=0.6.7
Requires-Dist: dataclasses>=0.6
Dynamic: license-file
